README.md
setup.cfg
setup.py
orbis/__init__.py
orbis/client.py
orbis.egg-info/PKG-INFO
orbis.egg-info/SOURCES.txt
orbis.egg-info/dependency_links.txt
orbis.egg-info/requires.txt
orbis.egg-info/top_level.txt