Metadata-Version: 1.1
Name: orbis
Version: 0.3
Summary: A random test lib
Home-page: https://github.com/peterldowns/mypackage
Author: Chanwoo Lee
Author-email: cjswosa2@gmail.com
License: UNKNOWN
Download-URL: https://github.com/leechanwoo/orbistest/blob/master/tfclient_package/package.tar
Keywords: testing,logging,example
Platform: UNKNOWN
